apttusvisualizations
