Metadata-Version: 1.1
Name: apttusvisualizations
Version: 0.11
Summary: Data visualizations for Apttus.
Home-page: https://github.com/cgowdy-apttus/apttusvisualizations
Author: Caitlin Gowdy at Apttus
Author-email: cgowdy@apttus.com
License: MIT
Download-URL: https://github.com/cgowdy-apttus/apttusvisualizations/archive/v_01.tar.gz
Platform: UNKNOWN
